nestedcvtraining/__init__.py
nestedcvtraining/api.py
nestedcvtraining/switch_case.py
nestedcvtraining/under_sampling_classifier.py
nestedcvtraining/utils/__init__.py
nestedcvtraining/utils/reporting.py
nestedcvtraining/utils/training.py
nestedcvtraining-1.1.dist-info/LICENSE.txt
nestedcvtraining-1.1.dist-info/METADATA
nestedcvtraining-1.1.dist-info/WHEEL
nestedcvtraining-1.1.dist-info/top_level.txt
nestedcvtraining-1.1.dist-info/RECORD
