Metadata-Version: 2.1
Name: nestedcvtraining
Version: 1.1
Summary: Perform Nested Cross Validation for model training
Home-page: https://github.com/JaimeArboleda/nestedcvtraining
Author: JaimeArboleda
Author-email: jaime.arboleda.castilla@gmail.com
License: MIT License
License-File: LICENSE.txt
Requires-Dist: pandas
Requires-Dist: imblearn
Requires-Dist: numpy
Requires-Dist: scikit-learn
Requires-Dist: scikit-optimize
